[{"word": "Breakfast", "start": 0.15, "end": 0.9}, {"word": "is", "start": 0.9, "end": 1.067}, {"word": "the", "start": 1.067, "end": 1.317}, {"word": "most", "start": 1.317, "end": 1.65}, {"word": "important", "start": 1.65, "end": 2.4}, {"word": "meal", "start": 2.4, "end": 2.733}, {"word": "of", "start": 2.733, "end": 2.9}, {"word": "the", "start": 2.9, "end": 3.15}, {"word": "day.", "start": 3.15, "end": 3.4}, {"word": "It", "start": 3.4, "end": 3.571}, {"word": "gives", "start": 3.571, "end": 3.997}, {"word": "you", "start": 3.997, "end": 4.253}, {"word": "energy", "start": 4.253, "end": 4.765}, {"word": "to", "start": 4.765, "end": 4.936}, {"word": "start", "start": 4.936, "end": 5.362}, {"word": "your", "start": 5.362, "end": 5.703}, {"word": "morning.", "start": 5.703, "end": 6.300000000000001}, {"word": "Many", "start": 6.35, "end": 6.746}, {"word": "people", "start": 6.746, "end": 7.34}, {"word": "eat", "start": 7.34, "end": 7.637}, {"word": "eggs,", "start": 7.637, "end": 8.033}, {"word": "bread,", "start": 8.033, "end": 8.528}, {"word": "and", "start": 8.528, "end": 8.825}, {"word": "milk", "start": 8.825, "end": 9.221}, {"word": "for", "start": 9.221, "end": 9.518}, {"word": "breakfast.", "start": 9.518, "end": 10.411999999999999}]