[{"word": "The", "start": 0.15, "end": 0.399}, {"word": "Viking", "start": 0.399, "end": 0.898}, {"word": "Age", "start": 0.898, "end": 1.147}, {"word": "was", "start": 1.147, "end": 1.396}, {"word": "a", "start": 1.396, "end": 1.479}, {"word": "period", "start": 1.479, "end": 1.978}, {"word": "of", "start": 1.978, "end": 2.144}, {"word": "history", "start": 2.144, "end": 2.726}, {"word": "when", "start": 2.726, "end": 3.058}, {"word": "Scandinavian", "start": 3.058, "end": 4.055}, {"word": "seafarers", "start": 4.055, "end": 4.803}, {"word": "called", "start": 4.803, "end": 5.302}, {"word": "Vikings", "start": 5.302, "end": 5.884}, {"word": "explored", "start": 5.884, "end": 6.549}, {"word": "and", "start": 6.549, "end": 6.798}, {"word": "settled", "start": 6.798, "end": 7.38}, {"word": "in", "start": 7.38, "end": 7.546}, {"word": "new", "start": 7.546, "end": 7.795}, {"word": "lands.", "start": 7.795, "end": 8.213}, {"word": "Between", "start": 8.212, "end": 8.788}, {"word": "the", "start": 8.788, "end": 9.035}, {"word": "8th", "start": 9.035, "end": 9.282}, {"word": "and", "start": 9.282, "end": 9.529}, {"word": "11th", "start": 9.529, "end": 9.858}, {"word": "centuries,", "start": 9.858, "end": 10.598}, {"word": "Vikings", "start": 10.598, "end": 11.174}, {"word": "traveled", "start": 11.174, "end": 11.832}, {"word": "to", "start": 11.832, "end": 11.997}, {"word": "places", "start": 11.997, "end": 12.491}, {"word": "like", "start": 12.491, "end": 12.82}, {"word": "North", "start": 12.82, "end": 13.231}, {"word": "America,", "start": 13.231, "end": 13.807}, {"word": "Russia,", "start": 13.807, "end": 14.301}, {"word": "and", "start": 14.301, "end": 14.548}, {"word": "the", "start": 14.548, "end": 14.795}, {"word": "Mediterranean.", "start": 14.795, "end": 15.862000000000002}, {"word": "Their", "start": 15.913, "end": 16.283}, {"word": "shipbuilding", "start": 16.283, "end": 17.172}, {"word": "and", "start": 17.172, "end": 17.394}, {"word": "navigation", "start": 17.394, "end": 18.135}, {"word": "skills", "start": 18.135, "end": 18.58}, {"word": "were", "start": 18.58, "end": 18.876}, {"word": "remarkable", "start": 18.876, "end": 19.617}, {"word": "for", "start": 19.617, "end": 19.839}, {"word": "the", "start": 19.839, "end": 20.061}, {"word": "time,", "start": 20.061, "end": 20.357}, {"word": "allowing", "start": 20.357, "end": 20.95}, {"word": "them", "start": 20.95, "end": 21.246}, {"word": "to", "start": 21.246, "end": 21.394}, {"word": "undertake", "start": 21.394, "end": 22.061}, {"word": "long", "start": 22.061, "end": 22.357}, {"word": "voyages", "start": 22.357, "end": 22.876}, {"word": "across", "start": 22.876, "end": 23.321}, {"word": "unknown", "start": 23.321, "end": 23.84}, {"word": "seas.", "start": 23.84, "end": 24.137999999999998}]