[{"word": "Every", "start": 0.15, "end": 0.582}, {"word": "evening,", "start": 0.582, "end": 1.187}, {"word": "Sarah", "start": 1.187, "end": 1.619}, {"word": "reads", "start": 1.619, "end": 2.051}, {"word": "a", "start": 2.051, "end": 2.137}, {"word": "book", "start": 2.137, "end": 2.483}, {"word": "for", "start": 2.483, "end": 2.742}, {"word": "one", "start": 2.742, "end": 3.001}, {"word": "hour", "start": 3.001, "end": 3.347}, {"word": "before", "start": 3.347, "end": 3.865}, {"word": "bed.", "start": 3.865, "end": 4.125}, {"word": "This", "start": 4.125, "end": 4.499}, {"word": "habit", "start": 4.499, "end": 4.967}, {"word": "helps", "start": 4.967, "end": 5.435}, {"word": "her", "start": 5.435, "end": 5.716}, {"word": "fall", "start": 5.716, "end": 6.09}, {"word": "asleep", "start": 6.09, "end": 6.651}, {"word": "easily.", "start": 6.651, "end": 7.213}, {"word": "Reading", "start": 7.263, "end": 7.865}, {"word": "is", "start": 7.865, "end": 8.037}, {"word": "her", "start": 8.037, "end": 8.295}, {"word": "favorite", "start": 8.295, "end": 8.983}, {"word": "way", "start": 8.983, "end": 9.241}, {"word": "to", "start": 9.241, "end": 9.413}, {"word": "relax", "start": 9.413, "end": 9.843}, {"word": "after", "start": 9.843, "end": 10.273}, {"word": "a", "start": 10.273, "end": 10.359}, {"word": "busy", "start": 10.359, "end": 10.703}, {"word": "day.", "start": 10.703, "end": 10.963000000000001}]