[{"word": "The", "start": 0.15, "end": 0.348}, {"word": "nexus", "start": 0.348, "end": 0.678}, {"word": "between", "start": 0.678, "end": 1.14}, {"word": "anthropogenic", "start": 1.14, "end": 1.998}, {"word": "climate", "start": 1.998, "end": 2.46}, {"word": "perturbations", "start": 2.46, "end": 3.318}, {"word": "and", "start": 3.318, "end": 3.516}, {"word": "biodiversity", "start": 3.516, "end": 4.308}, {"word": "attrition", "start": 4.308, "end": 4.902}, {"word": "manifests", "start": 4.902, "end": 5.496}, {"word": "through", "start": 5.496, "end": 5.958}, {"word": "multifarious", "start": 5.958, "end": 6.75}, {"word": "mechanisms", "start": 6.75, "end": 7.41}, {"word": "that", "start": 7.41, "end": 7.674}, {"word": "operate", "start": 7.674, "end": 8.136}, {"word": "across", "start": 8.136, "end": 8.532}, {"word": "temporal", "start": 8.532, "end": 9.06}, {"word": "and", "start": 9.06, "end": 9.258}, {"word": "spatial", "start": 9.258, "end": 9.72}, {"word": "scales", "start": 9.72, "end": 10.116}, {"word": "of", "start": 10.116, "end": 10.248}, {"word": "unprecedented", "start": 10.248, "end": 11.106}, {"word": "complexity.", "start": 11.106, "end": 11.762}, {"word": "Whilst", "start": 11.763, "end": 12.174}, {"word": "incremental", "start": 12.174, "end": 12.927}, {"word": "mitigation", "start": 12.927, "end": 13.612}, {"word": "strategies", "start": 13.612, "end": 14.297}, {"word": "have", "start": 14.297, "end": 14.571}, {"word": "garnered", "start": 14.571, "end": 15.119}, {"word": "political", "start": 15.119, "end": 15.735}, {"word": "expediency,", "start": 15.735, "end": 16.42}, {"word": "their", "start": 16.42, "end": 16.762}, {"word": "palliative", "start": 16.762, "end": 17.447}, {"word": "efficacy", "start": 17.447, "end": 17.995}, {"word": "proves", "start": 17.995, "end": 18.406}, {"word": "demonstrably", "start": 18.406, "end": 19.227}, {"word": "inadequate", "start": 19.227, "end": 19.912}, {"word": "in", "start": 19.912, "end": 20.049}, {"word": "arresting", "start": 20.049, "end": 20.665}, {"word": "the", "start": 20.665, "end": 20.87}, {"word": "trajectory", "start": 20.87, "end": 21.555}, {"word": "of", "start": 21.555, "end": 21.692}, {"word": "ecological", "start": 21.692, "end": 22.377}, {"word": "tipping", "start": 22.377, "end": 22.856}, {"word": "points.", "start": 22.856, "end": 23.262999999999998}, {"word": "The", "start": 23.312, "end": 23.522}, {"word": "requisite", "start": 23.522, "end": 24.151}, {"word": "paradigmatic", "start": 24.151, "end": 24.99}, {"word": "shift", "start": 24.99, "end": 25.34}, {"word": "toward", "start": 25.34, "end": 25.759}, {"word": "regenerative", "start": 25.759, "end": 26.598}, {"word": "resource", "start": 26.598, "end": 27.157}, {"word": "stewardship", "start": 27.157, "end": 27.926}, {"word": "necessitates", "start": 27.926, "end": 28.765}, {"word": "not", "start": 28.765, "end": 28.975}, {"word": "merely", "start": 28.975, "end": 29.394}, {"word": "technological", "start": 29.394, "end": 30.303}, {"word": "innovation", "start": 30.303, "end": 31.002}, {"word": "or", "start": 31.002, "end": 31.142}, {"word": "policy", "start": 31.142, "end": 31.561}, {"word": "reformulation,", "start": 31.561, "end": 32.47}, {"word": "but", "start": 32.47, "end": 32.68}, {"word": "a", "start": 32.68, "end": 32.75}, {"word": "fundamental", "start": 32.75, "end": 33.519}, {"word": "reconceptualization", "start": 33.519, "end": 34.847}, {"word": "of", "start": 34.847, "end": 34.987}, {"word": "humanity's", "start": 34.987, "end": 35.616}, {"word": "ontological", "start": 35.616, "end": 36.385}, {"word": "relationship", "start": 36.385, "end": 37.224}, {"word": "with", "start": 37.224, "end": 37.504}, {"word": "non-human", "start": 37.504, "end": 38.063}, {"word": "biological", "start": 38.063, "end": 38.762}, {"word": "systems.", "start": 38.762, "end": 39.25}, {"word": "Furthermore,", "start": 39.3, "end": 40.04}, {"word": "the", "start": 40.04, "end": 40.242}, {"word": "exacerbating", "start": 40.242, "end": 41.049}, {"word": "influence", "start": 41.049, "end": 41.654}, {"word": "of", "start": 41.654, "end": 41.788}, {"word": "economic", "start": 41.788, "end": 42.326}, {"word": "systems", "start": 42.326, "end": 42.797}, {"word": "predicated", "start": 42.797, "end": 43.469}, {"word": "upon", "start": 43.469, "end": 43.738}, {"word": "perpetual", "start": 43.738, "end": 44.343}, {"word": "growth", "start": 44.343, "end": 44.746}, {"word": "imperatives", "start": 44.746, "end": 45.486}, {"word": "engenders", "start": 45.486, "end": 46.091}, {"word": "a", "start": 46.091, "end": 46.158}, {"word": "structural", "start": 46.158, "end": 46.83}, {"word": "incompatibility", "start": 46.83, "end": 47.838}, {"word": "with", "start": 47.838, "end": 48.107}, {"word": "the", "start": 48.107, "end": 48.309}, {"word": "biophysical", "start": 48.309, "end": 49.049}, {"word": "constraints", "start": 49.049, "end": 49.789}, {"word": "of", "start": 49.789, "end": 49.923}, {"word": "planetary", "start": 49.923, "end": 50.528}, {"word": "boundaries.", "start": 50.528, "end": 51.2}, {"word": "Consequently,", "start": 51.25, "end": 52.109}, {"word": "the", "start": 52.109, "end": 52.324}, {"word": "resolution", "start": 52.324, "end": 53.039}, {"word": "of", "start": 53.039, "end": 53.182}, {"word": "this", "start": 53.182, "end": 53.468}, {"word": "civilizational", "start": 53.468, "end": 54.47}, {"word": "predicament", "start": 54.47, "end": 55.257}, {"word": "demands", "start": 55.257, "end": 55.758}, {"word": "a", "start": 55.758, "end": 55.83}, {"word": "multidisciplinary", "start": 55.83, "end": 57.046}, {"word": "integration", "start": 57.046, "end": 57.833}, {"word": "of", "start": 57.833, "end": 57.976}, {"word": "ecological", "start": 57.976, "end": 58.691}, {"word": "science,", "start": 58.691, "end": 59.192}, {"word": "socioeconomic", "start": 59.192, "end": 60.122}, {"word": "restructuring,", "start": 60.122, "end": 61.052}, {"word": "and", "start": 61.052, "end": 61.267}, {"word": "philosophical", "start": 61.267, "end": 62.197}, {"word": "inquiry", "start": 62.197, "end": 62.698}, {"word": "into", "start": 62.698, "end": 62.984}, {"word": "anthropogenic", "start": 62.984, "end": 63.914}, {"word": "instrumentalism.", "start": 63.914, "end": 64.98700000000001}]