[{"word": "The", "start": 0.15, "end": 0.375}, {"word": "gut", "start": 0.375, "end": 0.6}, {"word": "microbiome,", "start": 0.6, "end": 1.348}, {"word": "comprising", "start": 1.348, "end": 2.096}, {"word": "trillions", "start": 2.096, "end": 2.77}, {"word": "of", "start": 2.77, "end": 2.92}, {"word": "microorganisms,", "start": 2.92, "end": 3.968}, {"word": "exerts", "start": 3.968, "end": 4.417}, {"word": "profound", "start": 4.417, "end": 5.016}, {"word": "influence", "start": 5.016, "end": 5.69}, {"word": "on", "start": 5.69, "end": 5.84}, {"word": "immune", "start": 5.84, "end": 6.289}, {"word": "function,", "start": 6.289, "end": 6.888}, {"word": "metabolic", "start": 6.888, "end": 7.562}, {"word": "processes,", "start": 7.562, "end": 8.236}, {"word": "and", "start": 8.236, "end": 8.461}, {"word": "even", "start": 8.461, "end": 8.76}, {"word": "neurological", "start": 8.76, "end": 9.658}, {"word": "health", "start": 9.658, "end": 10.107}, {"word": "through", "start": 10.107, "end": 10.631}, {"word": "the", "start": 10.631, "end": 10.856}, {"word": "gut-brain", "start": 10.856, "end": 11.455}, {"word": "axis.", "start": 11.455, "end": 11.75}, {"word": "Contemporary", "start": 11.75, "end": 12.674}, {"word": "research", "start": 12.674, "end": 13.29}, {"word": "has", "start": 13.29, "end": 13.521}, {"word": "elucidated", "start": 13.521, "end": 14.291}, {"word": "that", "start": 14.291, "end": 14.599}, {"word": "dysbiosis—an", "start": 14.599, "end": 15.446}, {"word": "imbalance", "start": 15.446, "end": 16.139}, {"word": "in", "start": 16.139, "end": 16.293}, {"word": "microbial", "start": 16.293, "end": 16.986}, {"word": "communities—predisposes", "start": 16.986, "end": 18.681}, {"word": "individuals", "start": 18.681, "end": 19.528}, {"word": "to", "start": 19.528, "end": 19.682}, {"word": "autoimmune", "start": 19.682, "end": 20.452}, {"word": "disorders,", "start": 20.452, "end": 21.145}, {"word": "obesity,", "start": 21.145, "end": 21.684}, {"word": "and", "start": 21.684, "end": 21.915}, {"word": "mood", "start": 21.915, "end": 22.223}, {"word": "disturbances.", "start": 22.223, "end": 23.15}, {"word": "Consequently,", "start": 23.2, "end": 24.067}, {"word": "dietary", "start": 24.067, "end": 24.573}, {"word": "interventions", "start": 24.573, "end": 25.512}, {"word": "promoting", "start": 25.512, "end": 26.162}, {"word": "microbial", "start": 26.162, "end": 26.812}, {"word": "diversity,", "start": 26.812, "end": 27.462}, {"word": "such", "start": 27.462, "end": 27.751}, {"word": "as", "start": 27.751, "end": 27.895}, {"word": "consuming", "start": 27.895, "end": 28.545}, {"word": "fermented", "start": 28.545, "end": 29.195}, {"word": "foods", "start": 29.195, "end": 29.556}, {"word": "and", "start": 29.556, "end": 29.773}, {"word": "prebiotic-rich", "start": 29.773, "end": 30.712}, {"word": "vegetables,", "start": 30.712, "end": 31.434}, {"word": "have", "start": 31.434, "end": 31.723}, {"word": "garnered", "start": 31.723, "end": 32.301}, {"word": "substantial", "start": 32.301, "end": 33.095}, {"word": "scientific", "start": 33.095, "end": 33.817}, {"word": "validation", "start": 33.817, "end": 34.539}, {"word": "as", "start": 34.539, "end": 34.683}, {"word": "therapeutic", "start": 34.683, "end": 35.477}, {"word": "modalities.", "start": 35.477, "end": 36.2}]