[{"word": "The", "start": 0.15, "end": 0.371}, {"word": "phenomenon", "start": 0.371, "end": 1.106}, {"word": "of", "start": 1.106, "end": 1.253}, {"word": "cognitive", "start": 1.253, "end": 1.915}, {"word": "dissonance", "start": 1.915, "end": 2.65}, {"word": "occurs", "start": 2.65, "end": 3.091}, {"word": "when", "start": 3.091, "end": 3.385}, {"word": "individuals", "start": 3.385, "end": 4.194}, {"word": "hold", "start": 4.194, "end": 4.488}, {"word": "two", "start": 4.488, "end": 4.709}, {"word": "conflicting", "start": 4.709, "end": 5.518}, {"word": "beliefs", "start": 5.518, "end": 6.033}, {"word": "or", "start": 6.033, "end": 6.18}, {"word": "values", "start": 6.18, "end": 6.621}, {"word": "simultaneously.", "start": 6.621, "end": 7.6499999999999995}, {"word": "This", "start": 7.65, "end": 7.929}, {"word": "psychological", "start": 7.929, "end": 8.835}, {"word": "discomfort", "start": 8.835, "end": 9.532}, {"word": "motivates", "start": 9.532, "end": 10.159}, {"word": "people", "start": 10.159, "end": 10.577}, {"word": "to", "start": 10.577, "end": 10.716}, {"word": "resolve", "start": 10.716, "end": 11.204}, {"word": "the", "start": 11.204, "end": 11.413}, {"word": "conflict", "start": 11.413, "end": 11.971}, {"word": "by", "start": 11.971, "end": 12.11}, {"word": "either", "start": 12.11, "end": 12.528}, {"word": "changing", "start": 12.528, "end": 13.086}, {"word": "their", "start": 13.086, "end": 13.434}, {"word": "beliefs,", "start": 13.434, "end": 13.922}, {"word": "seeking", "start": 13.922, "end": 14.41}, {"word": "rationalizations,", "start": 14.41, "end": 15.525}, {"word": "or", "start": 15.525, "end": 15.664}, {"word": "avoiding", "start": 15.664, "end": 16.222}, {"word": "information", "start": 16.222, "end": 16.989}, {"word": "that", "start": 16.989, "end": 17.268}, {"word": "strengthens", "start": 17.268, "end": 18.035}, {"word": "the", "start": 18.035, "end": 18.244}, {"word": "contradiction.", "start": 18.244, "end": 19.15}, {"word": "Understanding", "start": 19.2, "end": 20.156}, {"word": "this", "start": 20.156, "end": 20.45}, {"word": "mechanism", "start": 20.45, "end": 21.112}, {"word": "is", "start": 21.112, "end": 21.259}, {"word": "crucial", "start": 21.259, "end": 21.774}, {"word": "for", "start": 21.774, "end": 21.995}, {"word": "comprehending", "start": 21.995, "end": 22.951}, {"word": "human", "start": 22.951, "end": 23.319}, {"word": "behavior", "start": 23.319, "end": 23.907}, {"word": "and", "start": 23.907, "end": 24.128}, {"word": "persuasion.", "start": 24.128, "end": 24.863}]